.dockerignore
.gitignore
CMakeLists.txt
Dockerfile
README.md
make.sh
pyproject.toml
setup.cfg
setup.py
.github/workflows/docker-publish.yml
CMakeModules/code-coverage.cmake
CMakeModules/pytest.cmake
bindings/CMakeLists.txt
bindings/conceptual.cpp
bindings/pybind11_opencv.hpp
bindings/conceptual/__init__.py
bindings/conceptual/dimensions.py
bindings/conceptual/learning.py
bindings/conceptual/query.py
bindings/conceptual/sources/__init__.py
bindings/conceptual/sources/gqa_source.py
bindings/conceptual/sources/source.py
bindings/conceptual/sources/vrd_source.py
conceptual.egg-info/PKG-INFO
conceptual.egg-info/SOURCES.txt
conceptual.egg-info/dependency_links.txt
conceptual.egg-info/not-zip-safe
conceptual.egg-info/requires.txt
conceptual.egg-info/top_level.txt
external/CMakeLists.txt
library/CMakeLists.txt
library/dimensions.cpp
library/graph.cpp
library/representation.cpp
library/space.cpp
library/structs.cpp
library/include/conceptual/core.hpp
library/include/conceptual/dimensions.hpp
library/include/conceptual/graph.hpp
library/include/conceptual/representation.hpp
library/include/conceptual/space.hpp
library/include/conceptual/structs.hpp
library/include/conceptual/utils.hpp
scripts/build_python.sh
scripts/install_opencv.sh
scripts/run_tests.sh
scripts/upload_package.sh
tests/CMakeLists.txt
tests/identifiers.cpp
tests/main.cpp
tests/space.cpp
tests/test.py
tests/test_gqa.py
tests/test_space.py
tests/test_vrd.py
tests/images/rose-whimsy.jpg