Metadata-Version: 1.0
Name: conceptual
Version: 0.1.0.6
Summary: Conceptual spaces for vision implementation
Home-page: UNKNOWN
Author: Daniel Koudouna
Author-email: dzk@st-andrews.ac.uk
License: UNKNOWN
Platform: UNKNOWN
